MANIFEST.in
setup.py
lyft_av_loo/__init__.py
lyft_av_loo/test.txt
lyft_av_loo.egg-info/PKG-INFO
lyft_av_loo.egg-info/SOURCES.txt
lyft_av_loo.egg-info/dependency_links.txt
lyft_av_loo.egg-info/not-zip-safe
lyft_av_loo.egg-info/top_level.txt