Metadata-Version: 1.0
Name: lyft-av-loo
Version: 0.5
Summary: AV learning on the loo
Home-page: https://github.com/lyft/avsoftware
Author: Jerry Yang, Shawn Liu
Author-email: av-scenarios@lyft.com
License: MIT
Platform: UNKNOWN
